setup.py
py_grabber/__init__.py
py_grabber/app.py
py_grabber/application.py
py_grabber/filesaver.py
py_grabber/htmlextractor.py
py_grabber/templates.py
py_grabber/textformatter.py
py_grabber/webdownloader.py
py_grabber.egg-info/PKG-INFO
py_grabber.egg-info/SOURCES.txt
py_grabber.egg-info/dependency_links.txt
py_grabber.egg-info/entry_points.txt
py_grabber.egg-info/requires.txt
py_grabber.egg-info/top_level.txt
tests/__init__.py
tests/templateloader.py
tests/textformatter.py