Metadata-Version: 1.1
Name: py-grabber
Version: 0.1.3
Summary: Extract main content from web-page
Home-page: https://github.com/kirillsulim/py-grabber
Author: Kirill Sulim
Author-email: kirillsulim@gmail.com
License: UNKNOWN
Platform: UNKNOWN
Classifier: Development Status :: 4 - Beta
Classifier: Environment :: Console
Classifier: Intended Audience :: End Users/Desktop
Classifier: License :: OSI Approved :: MIT License
Classifier: Natural Language :: English
Classifier: Operating System :: OS Independent
Classifier: Programming Language :: Python :: 3.3
Classifier: Programming Language :: Python :: 3.4
Classifier: Topic :: Internet :: WWW/HTTP
